electrickiwi_api/__init__.py
electrickiwi_api/api.py
electrickiwi_api/auth.py
electrickiwi_api/exceptions.py
electrickiwi_api/model.py
electrickiwi_api/py.typed
electrickiwi_api-0.9.13.dist-info/LICENSE
electrickiwi_api-0.9.13.dist-info/METADATA
electrickiwi_api-0.9.13.dist-info/WHEEL
electrickiwi_api-0.9.13.dist-info/RECORD
