Metadata-Version: 2.3
Name: electrickiwi-api
Version: 0.9.13
Summary: 
License: GPL-3.0
Author: Michael Arthur
Author-email: michael@jumblesoft.co.nz
Requires-Python: >=3.9
Classifier: License :: OSI Approved :: GNU General Public License v3 (GPLv3)
Classifier: Programming Language :: Python :: 3
Classifier: Programming Language :: Python :: 3.9
Classifier: Programming Language :: Python :: 3.10
Classifier: Programming Language :: Python :: 3.11
Classifier: Programming Language :: Python :: 3.12
Classifier: Programming Language :: Python :: 3.13
Requires-Dist: aiohttp (>=3.8.1)
Project-URL: Homepage, https://github.com/mikey0000/EK-API
